{"cameraMode":{"drawMode":0,"name":"Shaded","section":"Shading Mode"},"sceneLighting":true,"audioPlay":false,"sceneViewState":{"showFog":true,"showMaterialUpdate":false,"showSkybox":true,"showFlares":true,"showImageEffects":true,"showParticleSystems":true},"in2DMode":false,"pivot":{"x":412.74676513671877,"y":52.69464874267578,"z":-36.55326461791992},"rotation":{"x":0.1286114752292633,"y":0.03156548738479614,"z":-0.004090399947017431,"w":0.9911841750144959},"size":25.465787887573243,"orthographic":false}